bayesian_testing/__init__.py
bayesian_testing/experiments/__init__.py
bayesian_testing/experiments/base.py
bayesian_testing/experiments/binary.py
bayesian_testing/experiments/delta_lognormal.py
bayesian_testing/experiments/delta_normal.py
bayesian_testing/experiments/discrete.py
bayesian_testing/experiments/exponential.py
bayesian_testing/experiments/normal.py
bayesian_testing/experiments/poisson.py
bayesian_testing/metrics/__init__.py
bayesian_testing/metrics/evaluation.py
bayesian_testing/metrics/posteriors.py
bayesian_testing/utilities/__init__.py
bayesian_testing/utilities/common.py
bayesian_testing/utilities/logging.conf
bayesian_testing/utilities/logging.py
bayesian_testing-0.9.1.dist-info/LICENSE
bayesian_testing-0.9.1.dist-info/METADATA
bayesian_testing-0.9.1.dist-info/WHEEL
bayesian_testing-0.9.1.dist-info/RECORD
