Metadata-Version: 2.3
Name: bayesian-testing
Version: 0.9.1
Summary: Bayesian A/B testing with simple probabilities.
License: MIT
Keywords: ab testing,bayes,bayesian statistics
Author: Matus Baniar
Requires-Python: >=3.8
Classifier: License :: OSI Approved :: MIT License
Classifier: Programming Language :: Python :: 3
Classifier: Programming Language :: Python :: 3.8
Classifier: Programming Language :: Python :: 3.9
Classifier: Programming Language :: Python :: 3.10
Classifier: Programming Language :: Python :: 3.11
Classifier: Programming Language :: Python :: 3.12
Classifier: Programming Language :: Python :: 3.13
Requires-Dist: numpy (>=1.19)
Project-URL: Homepage, https://github.com/Matt52/bayesian-testing
Project-URL: Repository, https://github.com/Matt52/bayesian-testing
